topsis_101703161_A_deven-1.0.0.dist-info/METADATA
topsis_101703161_A_deven-1.0.0.dist-info/RECORD
topsis_101703161_A_deven-1.0.0.dist-info/WHEEL
topsis_101703161_A_deven-1.0.0.dist-info/entry_points.txt
topsis_101703161_A_deven-1.0.0.dist-info/top_level.txt
topsis_python/topsis.py
